flaskord/__init__.py
flaskord/exceptions.py
flaskord/flaskord.py
flaskord/oauth2.py
flaskord-0.2.3.dist-info/LICENSE
flaskord-0.2.3.dist-info/METADATA
flaskord-0.2.3.dist-info/WHEEL
flaskord-0.2.3.dist-info/top_level.txt
flaskord-0.2.3.dist-info/RECORD
